streamtick/__init__.py
streamtick/app.py
streamtick/arima.py
streamtick/data_acquisition.py
streamtick/data_preprocessing.py
streamtick/ui.py
streamtick-0.1.0.dist-info/METADATA
streamtick-0.1.0.dist-info/WHEEL
streamtick-0.1.0.dist-info/top_level.txt
streamtick-0.1.0.dist-info/RECORD
