Metadata-Version: 2.4
Name: StreamTick
Version: 0.1.0
Summary: A dynamic Streamlit library for stock time-series forecasting using ARIMA and Monte Carlo simulations.
Author-email: Nika Beruashvili <n.beruahvili2005@gmail.com>
License: MIT
Classifier: Development Status :: 3 - Alpha
Classifier: Intended Audience :: Developers
Classifier: Topic :: Software Development :: Build Tools
Classifier: Programming Language :: Python :: 3
Classifier: Programming Language :: Python :: 3.8
Classifier: Programming Language :: Python :: 3.9
Classifier: Programming Language :: Python :: 3.10
Requires-Python: >=3.8
Requires-Dist: pandas
Requires-Dist: numpy
Requires-Dist: statsmodels
Requires-Dist: pmdarima
Requires-Dist: streamlit
Requires-Dist: yfinance
Requires-Dist: plotly
